env_utils/__init__.py
env_utils-1.2.0.dist-info/DESCRIPTION.rst
env_utils-1.2.0.dist-info/METADATA
env_utils-1.2.0.dist-info/metadata.json
env_utils-1.2.0.dist-info/RECORD
env_utils-1.2.0.dist-info/top_level.txt
env_utils-1.2.0.dist-info/WHEEL
