Metadata-Version: 2.0
Name: env-utils
Version: 1.2.0
Summary: Utility functions to make it easier to work with os.environ
Home-page: https://github.com/yunojuno/python-env-utils
Author: Hugo Rodger-Brown
Author-email: hugo@yunojuno.com
License: MIT
Platform: UNKNOWN
Classifier: Intended Audience :: Developers
Classifier: License :: OSI Approved :: BSD License
Classifier: Operating System :: OS Independent
Classifier: Programming Language :: Python
Classifier: Programming Language :: Python :: 2.7
Requires-Dist: python-dateutil (>=2.6)
